pyfirst/__init__.py
pyfirst/pyfirst.py
pyfirst-1.0.2.dist-info/LICENCE
pyfirst-1.0.2.dist-info/METADATA
pyfirst-1.0.2.dist-info/WHEEL
pyfirst-1.0.2.dist-info/RECORD
