Metadata-Version: 2.3
Name: pyfirst
Version: 1.0.2
Summary: Factor Importance Ranking and Selection using Total Indices
License: MIT
Author: Chaofan Huang
Author-email: chuang397@gatech.edu
Maintainer: Chaofan Huang
Maintainer-email: chuang397@gatech.edu
Requires-Python: >=3.7.1
Classifier: License :: OSI Approved :: MIT License
Classifier: Operating System :: OS Independent
Classifier: Programming Language :: Python :: 3
Classifier: Programming Language :: Python :: 3.8
Classifier: Programming Language :: Python :: 3.9
Classifier: Programming Language :: Python :: 3.10
Classifier: Programming Language :: Python :: 3.11
Classifier: Programming Language :: Python :: 3.12
Classifier: Programming Language :: Python :: 3.13
Requires-Dist: faiss-cpu (>=1.7.4)
Requires-Dist: numpy (>=1.20.3)
Requires-Dist: pandas (>=1.3.4)
Requires-Dist: scikit-learn (>=0.24.2)
Requires-Dist: twinning (>=1.0.0)
Project-URL: Documentation, https://pyfirst.readthedocs.io/
Project-URL: Homepage, https://github.com/BillHuang01/pyfirst
Project-URL: Repository, https://github.com/BillHuang01/pyfirst.git
